{
  "name": "Evelyn Simon",
  "age": 24,
  "address": {
    "street": "Puwuv Lane",
    "city": "Wocesi",
    "state": "NE",
    "zip": "95843"
  },
  "contact": {
    "phone": "(528) 307-4252",
    "servicePhone": "800413576"
  },
  "birthday": "2001-05-06T07:10:50.797Z",
  "ip": "137.136.205.81",
  "foo": "bar",
  "profile": {
    "about": "Rinpu kukfemec ni kebabda ewi do he rimuwtaz imazesfow ecpiri posoz got. Vatrodjit ahi mo nadza wasupgin co cawatwo tizadko jekur nibaf ne esote nef so pejfud. Upte te busilweh tani toroc iloset nirujba cuztehhi li zotoz fatale ripu ubilocone udena sosaj.",
    "bio": "Lave pe obeaha ib jo uglewuk guliz pujbeimi ig jubaw hezuf gutigduc uzkili ewe huwutonof biloltu zihefde mufevpo. Copcozruz jow da tem utefu puc amgebo gedgeba pucid iglanik suk vekuaj noec navirwu er sastubin iznen hafa. Gijera ekamiep fag ju dudfa ikdu zehowic ho racufgin li wacur fo osaile haacsu pet buho imvuwwez da. Ke gaohilen cejebu etiap zuazcad metlalum guwonre ha buwil hivtomcec lufcemji kapdah. Pik vi mibo wanzoid kosesba ejko hovo cuwcav odsuhog ujmoas ret muovor. Zithube pargecjar hihag monmizor hecin te gug kasmovi baekaba tanpafbos iroz jaivohoh bu ke kartuwpif pozza zahzifag metme. Ujuiri zajej zeg pupvowedi jip tij vibal ezdenzu di ideas gaezo sopa mi setverfo fawre nofhapgup pa rome."
  },
  "apiKey": "3b0335e128291dc877e270de461f2a5e6c4b7e4635025d81c553fb987b3fc960",
  "currency": {
    "code": "GEL",
    "name": "Georgia Lari"
  }
}