{
  "name": "Georgie Soto",
  "age": 39,
  "address": {
    "street": "Miefe Court",
    "city": "Huupeca",
    "state": "MT",
    "zip": "16539"
  },
  "contact": {
    "phone": "(512) 710-9532",
    "servicePhone": "800726267"
  },
  "birthday": "2004-04-16T07:04:29.345Z",
  "ip": "33.188.60.98",
  "foo": "bar",
  "profile": {
    "about": "Rap alisej luizup vigutifo dacirhir weukre pew hetraf ruom pozos fe fo. Gugek fadehfu jisokaw ajkun codu nin pe tunil ajku tiharla eco riseje jik cecoc wo. Fa cided mitamkid ralbavade lowodi duhed vul uwo bu legobab okfocso jurebmis. Siwbuh kawnigfo absom apco muuf rijiewo zolaeb na ihukujpo li kifwimu kirwoha bungipeb gi obuzoc keli. Lur lirir omu gotocugi serec segle usaton pabvem koz pe terbo vosa.",
    "bio": "Rovumlid kavusso joterre rev op igeinahe fugje tib dalbuuc midlaw agawut biva. Gejca gu co ijkoge uto ongekjaf guztamu cofzu womu luloklo ko zizonedu usi sutu oba ebupe vonot. Rulo purkohe ig ehuric ojoulifuc hiah igoducpa riwmed luki buvufa tivu waumiwi datsajule. Arvedew kavpihe zub bo mi bepispuj or pi pedwajje kidosli ifmire vobtorcah piora tabi inta ajowipos zoze."
  },
  "apiKey": "2796c1393d1bd51bf4174ac4d1ca83e79a6c8244dfcae7f742be092790b34ac6",
  "currency": {
    "code": "LTL",
    "name": "Lithuania Litas"
  }
}